
[
    {
      "name": "Bitcoin",
      "symbol": "₿",
      "rank": 1,
      "age": 5024,
      "color": "#fa9e32",
      "png32": "https://lcw.nyc3.cdn.digitaloceanspaces.com/production/currencies/32/btc.png",
      "png64": "https://lcw.nyc3.cdn.digitaloceanspaces.com/production/currencies/64/btc.png",
      "webp32": "https://lcw.nyc3.cdn.digitaloceanspaces.com/production/currencies/32/btc.webp",
      "webp64": "https://lcw.nyc3.cdn.digitaloceanspaces.com/production/currencies/64/btc.webp",
      "exchanges": 208,
      "markets": 3952,
      "pairs": 1226,
      "categories": [],
      "allTimeHighUSD": 68780.77475755227,
      "circulatingSupply": 19170675,
      "totalSupply": 19170675,
      "maxSupply": 21000000,
      "website": "https://bitcoin.org/",
      "links": {
        "whitepaper": "https://bitcoin.org/bitcoin.pdf",
        "twitter": null,
        "reddit": "https://reddit.com/r/bitcoin",
        "telegram": null,
        "discord": null,
        "medium": null,
        "instagram": null
      },
      "code": "BTC",
      "rate": 20380.314174176103,
      "volume": 21014028394,
      "cap": 390704379431,
      "delta": {
        "hour": 0.999,
        "day": 1.0136,
        "week": 1.0426,
        "month": 1.0303,
        "quarter": 0.9265,
        "year": 0.3972
      }
    },
    {
      "name": "Ethereum",
      "symbol": "Ξ",
      "rank": 2,
      "age": 2625,
      "color": "#282a2a",
      "png32": "https://lcw.nyc3.cdn.digitaloceanspaces.com/production/currencies/32/eth.png",
      "png64": "https://lcw.nyc3.cdn.digitaloceanspaces.com/production/currencies/64/eth.png",
      "webp32": "https://lcw.nyc3.cdn.digitaloceanspaces.com/production/currencies/32/eth.webp",
      "webp64": "https://lcw.nyc3.cdn.digitaloceanspaces.com/production/currencies/64/eth.webp",
      "exchanges": 285,
      "markets": 4534,
      "pairs": 2258,
      "categories": [
        "smart_contract_platforms"
      ],
      "allTimeHighUSD": 4861.288700810894,
      "circulatingSupply": 122672317,
      "totalSupply": 122672317,
      "maxSupply": null,
      "website": "https://www.ethereum.org/",
      "links": {
        "whitepaper": "https://github.com/ethereum/wiki/wiki/White-Paper",
        "twitter": "https://twitter.com/ethereum",
        "reddit": "https://reddit.com/r/ethereum",
        "telegram": null,
        "discord": "https://discord.com/invite/CetY6Y4",
        "medium": null,
        "instagram": null
      },
      "code": "ETH",
      "rate": 1375.1535466582213,
      "volume": 7728435318,
      "cap": 168693271799,
      "delta": {
        "hour": 1.0001,
        "day": 1.0187,
        "week": 1.0253,
        "month": 0.8376,
        "quarter": 1.0958,
        "year": 0.3968
      }
    },
    {
      "name": "Tether",
      "rank": 3,
      "age": 3019,
      "color": "#e9f4f4",
      "png32": "https://lcw.nyc3.cdn.digitaloceanspaces.com/production/currencies/32/usdt.png",
      "png64": "https://lcw.nyc3.cdn.digitaloceanspaces.com/production/currencies/64/usdt.png",
      "webp32": "https://lcw.nyc3.cdn.digitaloceanspaces.com/production/currencies/32/usdt.webp",
      "webp64": "https://lcw.nyc3.cdn.digitaloceanspaces.com/production/currencies/64/usdt.webp",
      "exchanges": 262,
      "markets": 13318,
      "pairs": 4087,
      "categories": [
        "stablecoins"
      ],
      "allTimeHighUSD": 1.083725330741659,
      "circulatingSupply": 68212574445,
      "totalSupply": 68212574445,
      "maxSupply": null,
      "website": "https://tether.to",
      "links": {
        "whitepaper": "https://tether.to/wp-content/uploads/2015/04/Tether-White-Paper.pdf",
        "twitter": "https://twitter.com/tether_to",
        "reddit": "https://reddit.com/r/Tether",
        "telegram": "https://t.me/OfficialTether",
        "discord": null,
        "medium": null,
        "instagram": null
      },
      "code": "USDT",
      "rate": 1.0034651399094847,
      "volume": 32646446284,
      "cap": 68448940559,
      "delta": {
        "hour": 0.9997,
        "day": 1.0061,
        "week": 1.0014,
        "month": 1.003,
        "quarter": 0.9946,
        "year": 1.0025
      }
    },
    {
      "name": "USD Coin",
      "rank": 4,
      "age": 1458,
      "color": "#eef4f9",
      "png32": "https://lcw.nyc3.cdn.digitaloceanspaces.com/production/currencies/32/usdc.png",
      "png64": "https://lcw.nyc3.cdn.digitaloceanspaces.com/production/currencies/64/usdc.png",
      "webp32": "https://lcw.nyc3.cdn.digitaloceanspaces.com/production/currencies/32/usdc.webp",
      "webp64": "https://lcw.nyc3.cdn.digitaloceanspaces.com/production/currencies/64/usdc.webp",
      "exchanges": 215,
      "markets": 1642,
      "pairs": 860,
      "categories": [
        "stablecoins",
        "asset_backed_tokens"
      ],
      "allTimeHighUSD": 1.087,
      "circulatingSupply": 55663432949,
      "totalSupply": 55663432949,
      "maxSupply": null,
      "website": "https://www.centre.io/usdc",
      "links": {
        "whitepaper": "https://www.centre.io/pdfs/centre-whitepaper.pdf",
        "twitter": null,
        "reddit": null,
        "telegram": null,
        "discord": null,
        "medium": null,
        "instagram": null
      },
      "code": "USDC",
      "rate": 1.0027642729155832,
      "volume": 1816492095,
      "cap": 55817301869,
      "delta": {
        "hour": 0.9999,
        "day": 1.0081,
        "week": 1.0014,
        "month": 1.0046,
        "quarter": 1.0023,
        "year": 1.0027
      }
    },
    {
      "name": "BNB",
      "rank": 5,
      "age": 1923,
      "color": "#f4bc2c",
      "png32": "https://lcw.nyc3.cdn.digitaloceanspaces.com/production/currencies/32/bnb.png",
      "png64": "https://lcw.nyc3.cdn.digitaloceanspaces.com/production/currencies/64/bnb.png",
      "webp32": "https://lcw.nyc3.cdn.digitaloceanspaces.com/production/currencies/32/bnb.webp",
      "webp64": "https://lcw.nyc3.cdn.digitaloceanspaces.com/production/currencies/64/bnb.webp",
      "exchanges": 129,
      "markets": 3204,
      "pairs": 2698,
      "categories": [
        "cex",
        "smart_contract_platforms"
      ],
      "allTimeHighUSD": 691.55924082575,
      "circulatingSupply": 161337261,
      "totalSupply": 161337261,
      "maxSupply": 197192382,
      "website": "https://www.binance.com/",
      "links": {
        "whitepaper": "https://www.binance.com/resources/ico/Binance_WhitePaper_en.pdf",
        "twitter": "https://twitter.com/binance",
        "reddit": "https://reddit.com/r/binance",
        "telegram": "https://t.me/binanceexchange\\",
        "discord": "https://discord.com/invite/vKNp6qxw7a",
        "medium": "https://medium.com/@binance",
        "instagram": "https://instagram.com/Binance"
      },
      "code": "BNB",
      "rate": 296.2468132330881,
      "volume": 635193290,
      "cap": 47795649427,
      "delta": {
        "hour": 0.9974,
        "day": 1.0053,
        "week": 1.04,
        "month": 1.0541,
        "quarter": 1.2184,
        "year": 0.683
      }
    },
    {
      "name": "XRP",
      "rank": 6,
      "age": 3931,
      "color": "#040404",
      "png32": "https://lcw.nyc3.cdn.digitaloceanspaces.com/production/currencies/32/xrp.png",
      "png64": "https://lcw.nyc3.cdn.digitaloceanspaces.com/production/currencies/64/xrp.png",
      "webp32": "https://lcw.nyc3.cdn.digitaloceanspaces.com/production/currencies/32/xrp.webp",
      "webp64": "https://lcw.nyc3.cdn.digitaloceanspaces.com/production/currencies/64/xrp.webp",
      "exchanges": 110,
      "markets": 457,
      "pairs": 220,
      "categories": [
        "smart_contract_platforms"
      ],
      "allTimeHighUSD": 3.91546307780967,
      "circulatingSupply": 49858575704,
      "totalSupply": 99989275183,
      "maxSupply": 100000000000,
      "website": "https://ripple.com/",
      "links": {
        "whitepaper": "https://interledger.org/interledger.pdf",
        "twitter": "https://twitter.com/Ripple",
        "reddit": "https://reddit.com/r/ripple",
        "telegram": "https://t.me/Ripple",
        "discord": null,
        "medium": null,
        "instagram": null
      },
      "code": "XRP",
      "rate": 0.5028881419444441,
      "volume": 1863532710,
      "cap": 25073286496,
      "delta": {
        "hour": 1.009,
        "day": 1.0573,
        "week": 1.1286,
        "month": 1.5077,
        "quarter": 1.4196,
        "year": 0.4712
      }
    },
    {
      "name": "Binance USD",
      "rank": 7,
      "age": 1111,
      "color": "#f4bc0c",
      "png32": "https://lcw.nyc3.cdn.digitaloceanspaces.com/production/currencies/32/busd.png",
      "png64": "https://lcw.nyc3.cdn.digitaloceanspaces.com/production/currencies/64/busd.png",
      "webp32": "https://lcw.nyc3.cdn.digitaloceanspaces.com/production/currencies/32/busd.webp",
      "webp64": "https://lcw.nyc3.cdn.digitaloceanspaces.com/production/currencies/64/busd.webp",
      "exchanges": 86,
      "markets": 1225,
      "pairs": 923,
      "categories": [
        "stablecoins"
      ],
      "allTimeHighUSD": 1.24997330944831,
      "circulatingSupply": 21381640893,
      "totalSupply": 21381640893,
      "maxSupply": null,
      "website": "https://www.paxos.com/busd/",
      "links": {
        "whitepaper": null,
        "twitter": "https://twitter.com/PaxosGlobal",
        "reddit": null,
        "telegram": null,
        "discord": null,
        "medium": null,
        "instagram": null
      },
      "code": "BUSD",
      "rate": 1.0067144259477818,
      "volume": 1652159306,
      "cap": 21525206337,
      "delta": {
        "hour": 0.9991,
        "day": 0.9975,
        "week": 0.9985,
        "month": 1,
        "quarter": 1.0054,
        "year": 1.0085
      }
    },
    {
      "name": "Cardano",
      "rank": 8,
      "age": 1830,
      "color": "#226ed8",
      "png32": "https://lcw.nyc3.cdn.digitaloceanspaces.com/production/currencies/32/ada.png",
      "png64": "https://lcw.nyc3.cdn.digitaloceanspaces.com/production/currencies/64/ada.png",
      "webp32": "https://lcw.nyc3.cdn.digitaloceanspaces.com/production/currencies/32/ada.webp",
      "webp64": "https://lcw.nyc3.cdn.digitaloceanspaces.com/production/currencies/64/ada.webp",
      "exchanges": 71,
      "markets": 209,
      "pairs": 69,
      "categories": [
        "smart_contract_platforms"
      ],
      "allTimeHighUSD": 3.0939096930263132,
      "circulatingSupply": 34544852835,
      "totalSupply": 34544852835,
      "maxSupply": 45000000000,
      "website": "https://www.cardano.org/",
      "links": {
        "whitepaper": "https://www.cardanohub.org/en/academic-papers/",
        "twitter": "https://twitter.com/Cardano",
        "reddit": "https://reddit.com/r/cardano",
        "telegram": "https://t.me/cardano",
        "discord": null,
        "medium": null,
        "instagram": null
      },
      "code": "ADA",
      "rate": 0.43586261950921434,
      "volume": 348841658,
      "cap": 15056810047,
      "delta": {
        "hour": 0.9984,
        "day": 1.0108,
        "week": 0.9946,
        "month": 0.8723,
        "quarter": 0.9027,
        "year": 0.1978
      }
    },
    {
      "name": "Solana",
      "rank": 9,
      "age": 906,
      "color": "#68a1c9",
      "png32": "https://lcw.nyc3.cdn.digitaloceanspaces.com/production/currencies/32/sol.png",
      "png64": "https://lcw.nyc3.cdn.digitaloceanspaces.com/production/currencies/64/sol.png",
      "webp32": "https://lcw.nyc3.cdn.digitaloceanspaces.com/production/currencies/32/sol.webp",
      "webp64": "https://lcw.nyc3.cdn.digitaloceanspaces.com/production/currencies/64/sol.webp",
      "exchanges": 60,
      "markets": 200,
      "pairs": 87,
      "categories": [
        "smart_contract_platforms"
      ],
      "allTimeHighUSD": 259.8360337991446,
      "circulatingSupply": 355222484,
      "totalSupply": 530451598,
      "maxSupply": null,
      "website": "https://solana.com/",
      "links": {
        "whitepaper": "https://docs.solana.com/",
        "twitter": "https://twitter.com/solana",
        "reddit": "https://reddit.com/r/solana",
        "telegram": "https://t.me/solana",
        "discord": "https://discord.com/invite/pquxPsq",
        "medium": "https://medium.com/solana-labs",
        "instagram": "https://www.instagram.com/solana_updates"
      },
      "code": "SOL",
      "rate": 34.421447412264996,
      "volume": 541548461,
      "cap": 12227272053,
      "delta": {
        "hour": 1.001,
        "day": 1.0145,
        "week": 1.0187,
        "month": 1.0571,
        "quarter": 0.8985,
        "year": 0.2169
      }
    },
    {
      "name": "Dai",
      "rank": 10,
      "age": 1744,
      "color": "#fcb934",
      "png32": "https://lcw.nyc3.cdn.digitaloceanspaces.com/production/currencies/32/dai.png",
      "png64": "https://lcw.nyc3.cdn.digitaloceanspaces.com/production/currencies/64/dai.png",
      "webp32": "https://lcw.nyc3.cdn.digitaloceanspaces.com/production/currencies/32/dai.webp",
      "webp64": "https://lcw.nyc3.cdn.digitaloceanspaces.com/production/currencies/64/dai.webp",
      "exchanges": 110,
      "markets": 226,
      "pairs": 84,
      "categories": [
        "stablecoins"
      ],
      "allTimeHighUSD": 1.3998062062282162,
      "circulatingSupply": 9359045406,
      "totalSupply": 10931954334,
      "maxSupply": null,
      "website": "http://www.makerdao.com/",
      "links": {
        "whitepaper": "https://makerdao.com/whitepaper/",
        "twitter": "https://twitter.com/makerDAO",
        "reddit": "https://reddit.com/r/makerDAO",
        "telegram": "https://t.me/makerdaoOfficial",
        "discord": null,
        "medium": null,
        "instagram": null
      },
      "code": "DAI",
      "rate": 1.0020095482039748,
      "volume": 156325269,
      "cap": 9377852859,
      "delta": {
        "hour": 0.9997,
        "day": 1.0054,
        "week": 1.0029,
        "month": 1.0033,
        "quarter": 1.0016,
        "year": 1.0041
      }
    },
    {
      "name": "Dogecoin",
      "symbol": "Ɖ",
      "rank": 11,
      "age": 3216,
      "color": "#eee0b6",
      "png32": "https://lcw.nyc3.cdn.digitaloceanspaces.com/production/currencies/32/doge.png",
      "png64": "https://lcw.nyc3.cdn.digitaloceanspaces.com/production/currencies/64/doge.png",
      "webp32": "https://lcw.nyc3.cdn.digitaloceanspaces.com/production/currencies/32/doge.webp",
      "webp64": "https://lcw.nyc3.cdn.digitaloceanspaces.com/production/currencies/64/doge.webp",
      "exchanges": 95,
      "markets": 205,
      "pairs": 65,
      "categories": [
        "meme",
        "wallets",
        "charity"
      ],
      "allTimeHighUSD": 0.7371712183910056,
      "circulatingSupply": 132670764299,
      "totalSupply": 132670764299,
      "maxSupply": null,
      "website": "http://dogecoin.com/",
      "links": {
        "whitepaper": "https://dogecoin.com/dogepedia/",
        "twitter": "https://twitter.com/dogecoin",
        "reddit": "https://reddit.com/r/dogecoin",
        "telegram": null,
        "discord": "https://discord.com/invite/dogecoin",
        "medium": null,
        "instagram": null
      },
      "code": "DOGE",
      "rate": 0.06576058937550366,
      "volume": 416541642,
      "cap": 8724507653,
      "delta": {
        "hour": 0.9943,
        "day": 1.0116,
        "week": 1.0826,
        "month": 1.0408,
        "quarter": 0.9182,
        "year": 0.2584
      }
    },
    {
      "name": "Polkadot",
      "rank": 12,
      "age": 773,
      "color": "#e4047c",
      "png32": "https://lcw.nyc3.cdn.digitaloceanspaces.com/production/currencies/32/dot.png",
      "png64": "https://lcw.nyc3.cdn.digitaloceanspaces.com/production/currencies/64/dot.png",
      "webp32": "https://lcw.nyc3.cdn.digitaloceanspaces.com/production/currencies/32/dot.webp",
      "webp64": "https://lcw.nyc3.cdn.digitaloceanspaces.com/production/currencies/64/dot.webp",
      "exchanges": 79,
      "markets": 170,
      "pairs": 36,
      "categories": [
        "smart_contract_platforms"
      ],
      "allTimeHighUSD": 55.06538188283951,
      "circulatingSupply": 1150087198,
      "totalSupply": 1239248845,
      "maxSupply": null,
      "website": "https://polkadot.network/",
      "links": {
        "whitepaper": "https://polkadot.network/PolkaDotPaper.pdf",
        "twitter": "https://twitter.com/Polkadot",
        "reddit": "https://reddit.com/r/dot",
        "telegram": "https://t.me/PolkadotOfficial",
        "discord": "https://discord.com/invite/wGUDt2p",
        "medium": "https://medium.com/polkadot-network",
        "instagram": null
      },
      "code": "DOT",
      "rate": 6.481056545457672,
      "volume": 214985986,
      "cap": 7453780162,
      "delta": {
        "hour": 0.9988,
        "day": 1.012,
        "week": 1.0079,
        "month": 0.861,
        "quarter": 0.8861,
        "year": 0.2117
      }
    },
    {
      "name": "Polygon",
      "rank": 13,
      "age": 1256,
      "color": "#8444e4",
      "png32": "https://lcw.nyc3.cdn.digitaloceanspaces.com/production/currencies/32/matic.png",
      "png64": "https://lcw.nyc3.cdn.digitaloceanspaces.com/production/currencies/64/matic.png",
      "webp32": "https://lcw.nyc3.cdn.digitaloceanspaces.com/production/currencies/32/matic.webp",
      "webp64": "https://lcw.nyc3.cdn.digitaloceanspaces.com/production/currencies/64/matic.webp",
      "exchanges": 98,
      "markets": 407,
      "pairs": 228,
      "categories": [
        "smart_contract_platforms"
      ],
      "allTimeHighUSD": 2.920098783754804,
      "circulatingSupply": 8758817476,
      "totalSupply": 10000000000,
      "maxSupply": 10000000000,
      "website": "https://polygon.technology/",
      "links": {
        "whitepaper": "https://polygon.technology/lightpaper-polygon.pdf",
        "twitter": "https://twitter.com/0xPolygon",
        "reddit": "https://reddit.com/r/0xPolygon",
        "telegram": "https://t.me/maticnetwork",
        "discord": "https://discord.gg/tuETxzrh",
        "medium": "https://polygontech.medium.com/",
        "instagram": null
      },
      "code": "MATIC",
      "rate": 0.8492486359698816,
      "volume": 309655076,
      "cap": 7438413794,
      "delta": {
        "hour": 0.9999,
        "day": 1.017,
        "week": 1.1345,
        "month": 0.9594,
        "quarter": 1.4525,
        "year": 0.6688
      }
    },
    {
      "name": "Shiba Inu",
      "rank": 14,
      "age": 609,
      "color": "#faa00d",
      "png32": "https://lcw.nyc3.cdn.digitaloceanspaces.com/production/currencies/32/shib.png",
      "png64": "https://lcw.nyc3.cdn.digitaloceanspaces.com/production/currencies/64/shib.png",
      "webp32": "https://lcw.nyc3.cdn.digitaloceanspaces.com/production/currencies/32/shib.webp",
      "webp64": "https://lcw.nyc3.cdn.digitaloceanspaces.com/production/currencies/64/shib.webp",
      "exchanges": 74,
      "markets": 111,
      "pairs": 27,
      "categories": [
        "dex",
        "yield_farming",
        "meme"
      ],
      "allTimeHighUSD": 0.00008877244256117385,
      "circulatingSupply": 589320370665618,
      "totalSupply": 589618449629880,
      "maxSupply": null,
      "website": "https://shibatoken.com/",
      "links": {
        "whitepaper": "https://raw.githubusercontent.com/shytoshikusama/woofwoofpaper/main/SHIBA_INU_WOOF_WOOF.pdf",
        "twitter": "https://twitter.com/shibtoken",
        "reddit": "https://reddit.com/r/SHIBArmy",
        "telegram": "https://t.me/shibainuthedogecoinkiller",
        "discord": "https://discord.com/invite/shibatoken",
        "medium": "https://allhailtheshiba.medium.com",
        "instagram": null
      },
      "code": "SHIB",
      "rate": 0.000011583141254789853,
      "volume": 245633242,
      "cap": 6826181098,
      "delta": {
        "hour": 0.9956,
        "day": 1.0042,
        "week": 1.0294,
        "month": 0.9137,
        "quarter": 1.0249,
        "year": 0.5415
      }
    },
    {
      "name": "TRON",
      "rank": 15,
      "age": 1849,
      "color": "#c43429",
      "png32": "https://lcw.nyc3.cdn.digitaloceanspaces.com/production/currencies/32/trx.png",
      "png64": "https://lcw.nyc3.cdn.digitaloceanspaces.com/production/currencies/64/trx.png",
      "webp32": "https://lcw.nyc3.cdn.digitaloceanspaces.com/production/currencies/32/trx.webp",
      "webp64": "https://lcw.nyc3.cdn.digitaloceanspaces.com/production/currencies/64/trx.webp",
      "exchanges": 91,
      "markets": 265,
      "pairs": 75,
      "categories": [
        "storage",
        "smart_contract_platforms"
      ],
      "allTimeHighUSD": 0.2947430746031121,
      "circulatingSupply": 92336486563,
      "totalSupply": 92336487606,
      "maxSupply": null,
      "website": "https://tron.network/",
      "links": {
        "whitepaper": "https://o836fhe91.qnssl.com/tron/whitebook/TronWhitepaper_en.pdf",
        "twitter": "https://twitter.com/trondao",
        "reddit": "https://reddit.com/r/Tronix",
        "telegram": "https://t.me/tronnetworkEN",
        "discord": "https://discord.com/invite/ezNzd9W",
        "medium": "https://tronfoundation.medium.com/",
        "instagram": "https://instagram.com/tronfoundation"
      },
      "code": "TRX",
      "rate": 0.06332158292052588,
      "volume": 225822056,
      "cap": 5846892490,
      "delta": {
        "hour": 1.0001,
        "day": 1.0118,
        "week": 1.0399,
        "month": 0.9948,
        "quarter": 0.9086,
        "year": 0.6717
      }
    },
    {
      "name": "Uniswap",
      "rank": 16,
      "age": 749,
      "color": "#fc047c",
      "png32": "https://lcw.nyc3.cdn.digitaloceanspaces.com/production/currencies/32/uni.png",
      "png64": "https://lcw.nyc3.cdn.digitaloceanspaces.com/production/currencies/64/uni.png",
      "webp32": "https://lcw.nyc3.cdn.digitaloceanspaces.com/production/currencies/32/uni.webp",
      "webp64": "https://lcw.nyc3.cdn.digitaloceanspaces.com/production/currencies/64/uni.webp",
      "exchanges": 105,
      "markets": 186,
      "pairs": 32,
      "categories": [
        "dex",
        "yield_farming",
        "governance"
      ],
      "allTimeHighUSD": 45.009351908031135,
      "circulatingSupply": 768918425,
      "totalSupply": 1000000000,
      "maxSupply": 1000000000,
      "website": "https://uniswap.org/",
      "links": {
        "whitepaper": "https://uniswap.org/whitepaper-v3.pdf",
        "twitter": "https://twitter.com/Uniswap",
        "reddit": "https://reddit.com/r/Uniswap",
        "telegram": null,
        "discord": "https://discord.com/invite/FCfyBSbCU5",
        "medium": null,
        "instagram": null
      },
      "code": "UNI",
      "rate": 6.922996318736698,
      "volume": 122363872,
      "cap": 5323219426,
      "delta": {
        "hour": 0.9967,
        "day": 1.0425,
        "week": 1.0639,
        "month": 1.0579,
        "quarter": 1.1944,
        "year": 0.2771
      }
    },
    {
      "name": "Avalanche",
      "rank": 17,
      "age": 743,
      "color": "#eb4343",
      "png32": "https://lcw.nyc3.cdn.digitaloceanspaces.com/production/currencies/32/avax.png",
      "png64": "https://lcw.nyc3.cdn.digitaloceanspaces.com/production/currencies/64/avax.png",
      "webp32": "https://lcw.nyc3.cdn.digitaloceanspaces.com/production/currencies/32/avax.webp",
      "webp64": "https://lcw.nyc3.cdn.digitaloceanspaces.com/production/currencies/64/avax.webp",
      "exchanges": 65,
      "markets": 320,
      "pairs": 188,
      "categories": [
        "smart_contract_platforms"
      ],
      "allTimeHighUSD": 146.46571588270493,
      "circulatingSupply": 296098574,
      "totalSupply": 377752194,
      "maxSupply": 720000000,
      "website": "https://www.avax.network/",
      "links": {
        "whitepaper": "https://docs.avax.network/",
        "twitter": "https://twitter.com/avalancheavax",
        "reddit": "https://reddit.com/r/Avax",
        "telegram": "https://t.me/avalancheavax",
        "discord": "https://discord.com/invite/RwXY7P6",
        "medium": "https://medium.com/avalancheavax",
        "instagram": null
      },
      "code": "AVAX",
      "rate": 17.57467208121079,
      "volume": 129073459,
      "cap": 5203835342,
      "delta": {
        "hour": 1.0006,
        "day": 1.0159,
        "week": 1.0154,
        "month": 0.8834,
        "quarter": 0.8571,
        "year": 0.281
      }
    },
    {
      "name": "OKB",
      "rank": 18,
      "age": 1254,
      "color": "#ededed",
      "png32": "https://lcw.nyc3.cdn.digitaloceanspaces.com/production/currencies/32/okb.png",
      "png64": "https://lcw.nyc3.cdn.digitaloceanspaces.com/production/currencies/64/okb.png",
      "webp32": "https://lcw.nyc3.cdn.digitaloceanspaces.com/production/currencies/32/okb.webp",
      "webp64": "https://lcw.nyc3.cdn.digitaloceanspaces.com/production/currencies/64/okb.webp",
      "exchanges": 16,
      "markets": 25,
      "pairs": 11,
      "categories": [
        "cex"
      ],
      "allTimeHighUSD": 44.237843690801675,
      "circulatingSupply": 251627612,
      "totalSupply": 300000000,
      "maxSupply": 300000000,
      "website": "https://www.okx.com/",
      "links": {
        "whitepaper": "https://okexchain-docs.readthedocs.io/en/latest/",
        "twitter": "https://twitter.com/okx",
        "reddit": "https://reddit.com/r/OKEx",
        "telegram": "https://t.me/OECofficial",
        "discord": "https://discord.com/invite/2rynEUqJxP",
        "medium": "https://medium.com/okex-blog",
        "instagram": "https://www.instagram.com/okx_official/"
      },
      "code": "OKB",
      "rate": 15.814651301381897,
      "volume": 20979721,
      "cap": 3979402942,
      "delta": {
        "hour": 1.0021,
        "day": 1.0151,
        "week": 1.0223,
        "month": 1.0653,
        "quarter": 1.1967,
        "year": 0.9066
      }
    },
    {
      "name": "Litecoin",
      "rank": 19,
      "age": 4016,
      "color": "#345c9c",
      "png32": "https://lcw.nyc3.cdn.digitaloceanspaces.com/production/currencies/32/ltc.png",
      "png64": "https://lcw.nyc3.cdn.digitaloceanspaces.com/production/currencies/64/ltc.png",
      "webp32": "https://lcw.nyc3.cdn.digitaloceanspaces.com/production/currencies/32/ltc.webp",
      "webp64": "https://lcw.nyc3.cdn.digitaloceanspaces.com/production/currencies/64/ltc.webp",
      "exchanges": 136,
      "markets": 384,
      "pairs": 99,
      "categories": [],
      "allTimeHighUSD": 413.0840556096379,
      "circulatingSupply": 71323493,
      "totalSupply": 71323493,
      "maxSupply": 84000000,
      "website": "https://litecoin.com",
      "links": {
        "whitepaper": null,
        "twitter": "https://twitter.com/LitecoinDotCom",
        "reddit": "https://reddit.com/r/litecoin",
        "telegram": "https://t.me/litecoin",
        "discord": null,
        "medium": null,
        "instagram": "https://instagram.com/litecoindotcom"
      },
      "code": "LTC",
      "rate": 55.07264852346131,
      "volume": 342038485,
      "cap": 3927973661,
      "delta": {
        "hour": 0.9989,
        "day": 1.0062,
        "week": 1.0214,
        "month": 0.9126,
        "quarter": 1.025,
        "year": 0.3213
      }
    },
    {
      "name": "Ethereum Classic",
      "rank": 20,
      "age": 2264,
      "color": "#3ab93a",
      "png32": "https://lcw.nyc3.cdn.digitaloceanspaces.com/production/currencies/32/etc.png",
      "png64": "https://lcw.nyc3.cdn.digitaloceanspaces.com/production/currencies/64/etc.png",
      "webp32": "https://lcw.nyc3.cdn.digitaloceanspaces.com/production/currencies/32/etc.webp",
      "webp64": "https://lcw.nyc3.cdn.digitaloceanspaces.com/production/currencies/64/etc.webp",
      "exchanges": 76,
      "markets": 172,
      "pairs": 36,
      "categories": [
        "smart_contract_platforms"
      ],
      "allTimeHighUSD": 168.98136358110946,
      "circulatingSupply": 137230427,
      "totalSupply": 210700000,
      "maxSupply": 210700000,
      "website": "https://ethereumclassic.github.io/",
      "links": {
        "whitepaper": "https://github.com/ethereum/wiki/wiki/White-Paper",
        "twitter": "https://twitter.com/eth_classic",
        "reddit": "https://reddit.com/r/EthereumClassic",
        "telegram": null,
        "discord": "https://discord.gg/HW4GckH",
        "medium": null,
        "instagram": null
      },
      "code": "ETC",
      "rate": 28.53370015707749,
      "volume": 262986871,
      "cap": 3915691856,
      "delta": {
        "hour": 0.9987,
        "day": 1.027,
        "week": 1.0298,
        "month": 0.7051,
        "quarter": 1.7771,
        "year": 0.5374
      }
    },
    {
      "name": "Chainlink",
      "rank": 21,
      "age": 1846,
      "color": "#2959d9",
      "png32": "https://lcw.nyc3.cdn.digitaloceanspaces.com/production/currencies/32/link.png",
      "png64": "https://lcw.nyc3.cdn.digitaloceanspaces.com/production/currencies/64/link.png",
      "webp32": "https://lcw.nyc3.cdn.digitaloceanspaces.com/production/currencies/32/link.webp",
      "webp64": "https://lcw.nyc3.cdn.digitaloceanspaces.com/production/currencies/64/link.webp",
      "exchanges": 141,
      "markets": 286,
      "pairs": 50,
      "categories": [
        "oracle",
        "token_bridges",
        "security",
        "analytics"
      ],
      "allTimeHighUSD": 52.85091701629316,
      "circulatingSupply": 491599970,
      "totalSupply": 1000000000,
      "maxSupply": 1000000000,
      "website": "https://chain.link/",
      "links": {
        "whitepaper": "https://research.chain.link/whitepaper-v2.pdf?_ga=2.202988689.147345121.1621217890-329871762.1621217890",
        "twitter": "https://twitter.com/chainlink",
        "reddit": "https://reddit.com/r/chainlink",
        "telegram": "https://t.me/chainlinkofficial",
        "discord": "https://discord.gg/aSK4zew",
        "medium": null,
        "instagram": null
      },
      "code": "LINK",
      "rate": 7.880316090570342,
      "volume": 510611250,
      "cap": 3873963154,
      "delta": {
        "hour": 0.9948,
        "day": 1.0246,
        "week": 1.015,
        "month": 1.0847,
        "quarter": 1.1637,
        "year": 0.2963
      }
    },
    {
      "name": "FTX Token",
      "rank": 22,
      "age": 1149,
      "color": "#5cccdc",
      "png32": "https://lcw.nyc3.cdn.digitaloceanspaces.com/production/currencies/32/ftt.png",
      "png64": "https://lcw.nyc3.cdn.digitaloceanspaces.com/production/currencies/64/ftt.png",
      "webp32": "https://lcw.nyc3.cdn.digitaloceanspaces.com/production/currencies/32/ftt.webp",
      "webp64": "https://lcw.nyc3.cdn.digitaloceanspaces.com/production/currencies/64/ftt.webp",
      "exchanges": 45,
      "markets": 66,
      "pairs": 17,
      "categories": [
        "cex"
      ],
      "allTimeHighUSD": 83.82453603463195,
      "circulatingSupply": 133488350,
      "totalSupply": 329357686,
      "maxSupply": null,
      "website": "https://ftx.com",
      "links": {
        "whitepaper": "https://docs.google.com/document/d/1u5MOkENoWP8PGcjuoKqRkNP5Gl1LLRB9JvAHwffQ7ec/view",
        "twitter": "https://twitter.com/FTX_Official",
        "reddit": "https://reddit.com/r/FTX_Official",
        "telegram": "https://t.me/FTX_Official",
        "discord": null,
        "medium": "https://ftx.medium.com/",
        "instagram": "https://www.instagram.com/ftx_official"
      },
      "code": "FTT",
      "rate": 25.235376594621034,
      "volume": 44128195,
      "cap": 3368628783,
      "delta": {
        "hour": 0.9985,
        "day": 1.0099,
        "week": 1.0358,
        "month": 0.9387,
        "quarter": 0.9092,
        "year": 0.4456
      }
    },
    {
      "name": "Cosmos",
      "rank": 23,
      "age": 2187,
      "color": "#30334c",
      "png32": "https://lcw.nyc3.cdn.digitaloceanspaces.com/production/currencies/32/atom.png",
      "png64": "https://lcw.nyc3.cdn.digitaloceanspaces.com/production/currencies/64/atom.png",
      "webp32": "https://lcw.nyc3.cdn.digitaloceanspaces.com/production/currencies/32/atom.webp",
      "webp64": "https://lcw.nyc3.cdn.digitaloceanspaces.com/production/currencies/64/atom.webp",
      "exchanges": 54,
      "markets": 138,
      "pairs": 46,
      "categories": [
        "iot",
        "smart_contract_platforms"
      ],
      "allTimeHighUSD": 44.477623439842205,
      "circulatingSupply": 238524829,
      "totalSupply": 238524829,
      "maxSupply": null,
      "website": "https://cosmos.network/",
      "links": {
        "whitepaper": "https://cosmos.network/resources/whitepaper",
        "twitter": "https://twitter.com/cosmos",
        "reddit": "https://reddit.com/r/cosmosnetwork",
        "telegram": "https://t.me/cosmosproject",
        "discord": "https://discord.com/invite/cosmosnetwork",
        "medium": null,
        "instagram": null
      },
      "code": "ATOM",
      "rate": 13.136335279703697,
      "volume": 171493126,
      "cap": 3133342126,
      "delta": {
        "hour": 0.9951,
        "day": 1.0137,
        "week": 1.0106,
        "month": 1.0559,
        "quarter": 1.412,
        "year": 0.3774
      }
    },
    {
      "name": "Stellar",
      "rank": 24,
      "age": 2983,
      "color": "#040404",
      "png32": "https://lcw.nyc3.cdn.digitaloceanspaces.com/production/currencies/32/xlm.png",
      "png64": "https://lcw.nyc3.cdn.digitaloceanspaces.com/production/currencies/64/xlm.png",
      "webp32": "https://lcw.nyc3.cdn.digitaloceanspaces.com/production/currencies/32/xlm.webp",
      "webp64": "https://lcw.nyc3.cdn.digitaloceanspaces.com/production/currencies/64/xlm.webp",
      "exchanges": 78,
      "markets": 201,
      "pairs": 53,
      "categories": [
        "smart_contract_platforms"
      ],
      "allTimeHighUSD": 0.921644339265009,
      "circulatingSupply": 25495275036,
      "totalSupply": 50001787570,
      "maxSupply": null,
      "website": "https://www.stellar.org",
      "links": {
        "whitepaper": "https://www.stellar.org/papers/stellar-consensus-protocol.pdf",
        "twitter": "https://twitter.com/StellarOrg",
        "reddit": "https://reddit.com/r/stellar",
        "telegram": null,
        "discord": null,
        "medium": "https://medium.com/stellar-community",
        "instagram": null
      },
      "code": "XLM",
      "rate": 0.12033733575410865,
      "volume": 92437836,
      "cap": 3068033472,
      "delta": {
        "hour": 1.0023,
        "day": 1.0191,
        "week": 1.1041,
        "month": 1.1328,
        "quarter": 1.0328,
        "year": 0.3791
      }
    },
    {
      "name": "NEAR Protocol",
      "rank": 25,
      "age": 711,
      "color": "#040404",
      "png32": "https://lcw.nyc3.cdn.digitaloceanspaces.com/production/currencies/32/near.png",
      "png64": "https://lcw.nyc3.cdn.digitaloceanspaces.com/production/currencies/64/near.png",
      "webp32": "https://lcw.nyc3.cdn.digitaloceanspaces.com/production/currencies/32/near.webp",
      "webp64": "https://lcw.nyc3.cdn.digitaloceanspaces.com/production/currencies/64/near.webp",
      "exchanges": 64,
      "markets": 140,
      "pairs": 43,
      "categories": [
        "smart_contract_platforms"
      ],
      "allTimeHighUSD": 20.46907836312353,
      "circulatingSupply": 801803738,
      "totalSupply": 1000000000,
      "maxSupply": 1000000000,
      "website": "https://near.org/",
      "links": {
        "whitepaper": "https://docs.near.org/docs/develop/basics/getting-started",
        "twitter": "https://twitter.com/nearprotocol",
        "reddit": "https://reddit.com/r/nearprotocol",
        "telegram": "https://t.me/cryptonear",
        "discord": "https://discord.com/invite/UY9Xf2k",
        "medium": "https://medium.com/nearprotocol",
        "instagram": "https://www.instagram.com/near_protocol"
      },
      "code": "NEAR",
      "rate": 3.72649520186436,
      "volume": 268495149,
      "cap": 2987917782,
      "delta": {
        "hour": 0.9984,
        "day": 1.0353,
        "week": 1.0254,
        "month": 0.8672,
        "quarter": 1.0052,
        "year": 0.4874
      }
    },
    {
      "name": "Cronos",
      "rank": 26,
      "age": 1302,
      "color": "#f6f7f8",
      "png32": "https://lcw.nyc3.cdn.digitaloceanspaces.com/production/currencies/32/cro.png",
      "png64": "https://lcw.nyc3.cdn.digitaloceanspaces.com/production/currencies/64/cro.png",
      "webp32": "https://lcw.nyc3.cdn.digitaloceanspaces.com/production/currencies/32/cro.webp",
      "webp64": "https://lcw.nyc3.cdn.digitaloceanspaces.com/production/currencies/64/cro.webp",
      "exchanges": 35,
      "markets": 102,
      "pairs": 54,
      "categories": [
        "cex",
        "wallets",
        "debit_cards"
      ],
      "allTimeHighUSD": 0.9516849148075289,
      "circulatingSupply": 25263013692,
      "totalSupply": 30263013692,
      "maxSupply": null,
      "website": "https://www.crypto.com/en/chain",
      "links": {
        "whitepaper": "https://crypto.com/images/crypto_com_whitepaper.pdf",
        "twitter": "https://twitter.com/cryptocom",
        "reddit": "https://reddit.com/r/Crypto_com",
        "telegram": "https://t.me/CryptoComOfficial",
        "discord": "https://discord.com/invite/nsp9JTC",
        "medium": "https://medium.com/@crypto.com",
        "instagram": "https://instagram.com/cryptocomofficial"
      },
      "code": "CRO",
      "rate": 0.11121652834586383,
      "volume": 13037449,
      "cap": 2809664678,
      "delta": {
        "hour": 0.9997,
        "day": 1.0093,
        "week": 0.994,
        "month": 0.9339,
        "quarter": 0.889,
        "year": 0.6149
      }
    },
    {
      "name": "Monero",
      "rank": 27,
      "age": 3093,
      "color": "#fc6404",
      "png32": "https://lcw.nyc3.cdn.digitaloceanspaces.com/production/currencies/32/xmr.png",
      "png64": "https://lcw.nyc3.cdn.digitaloceanspaces.com/production/currencies/64/xmr.png",
      "webp32": "https://lcw.nyc3.cdn.digitaloceanspaces.com/production/currencies/32/xmr.webp",
      "webp64": "https://lcw.nyc3.cdn.digitaloceanspaces.com/production/currencies/64/xmr.webp",
      "exchanges": 39,
      "markets": 75,
      "pairs": 20,
      "categories": [
        "privacy_coins"
      ],
      "allTimeHighUSD": 516.843201123428,
      "circulatingSupply": 18081370,
      "totalSupply": 18081370,
      "maxSupply": null,
      "website": "http://www.monero.cc",
      "links": {
        "whitepaper": "https://github.com/monero-project/research-lab/blob/master/whitepaper/whitepaper.pdf",
        "twitter": "https://twitter.com/monero",
        "reddit": "https://reddit.com/r/monero",
        "telegram": "https://t.me/bitmonero",
        "discord": null,
        "medium": null,
        "instagram": null
      },
      "code": "XMR",
      "rate": 148.87554292904497,
      "volume": 76374291,
      "cap": 2691873776,
      "delta": {
        "hour": 0.9985,
        "day": 1.02,
        "week": 1.0071,
        "month": 0.9461,
        "quarter": 1.1196,
        "year": 0.5537
      }
    },
    {
      "name": "Algorand",
      "rank": 28,
      "age": 1202,
      "color": "#efefef",
      "png32": "https://lcw.nyc3.cdn.digitaloceanspaces.com/production/currencies/32/algo.png",
      "png64": "https://lcw.nyc3.cdn.digitaloceanspaces.com/production/currencies/64/algo.png",
      "webp32": "https://lcw.nyc3.cdn.digitaloceanspaces.com/production/currencies/32/algo.webp",
      "webp64": "https://lcw.nyc3.cdn.digitaloceanspaces.com/production/currencies/64/algo.webp",
      "exchanges": 48,
      "markets": 151,
      "pairs": 61,
      "categories": [
        "smart_contract_platforms"
      ],
      "allTimeHighUSD": 3.228152051480498,
      "circulatingSupply": 7015124135,
      "totalSupply": 10000000000,
      "maxSupply": 10000000000,
      "website": "http://algorand.foundation",
      "links": {
        "whitepaper": "https://www.algorand.com/resources/white-papers",
        "twitter": "https://twitter.com/AlgoFoundation",
        "reddit": "https://reddit.com/r/AlgorandOfficial",
        "telegram": "https://t.me/AlgorandFoundation",
        "discord": "https://discord.gg/84AActu3at",
        "medium": "https://medium.com/algorand",
        "instagram": null
      },
      "code": "ALGO",
      "rate": 0.357784596829473,
      "volume": 48120799,
      "cap": 2509903360,
      "delta": {
        "hour": 1.0019,
        "day": 1.0137,
        "week": 1.0117,
        "month": 1.1776,
        "quarter": 1.1053,
        "year": 0.1905
      }
    },
    {
      "name": "Wrapped Bitcoin",
      "rank": 29,
      "age": 1343,
      "color": "#f09444",
      "png32": "https://lcw.nyc3.cdn.digitaloceanspaces.com/production/currencies/32/wbtc.png",
      "png64": "https://lcw.nyc3.cdn.digitaloceanspaces.com/production/currencies/64/wbtc.png",
      "webp32": "https://lcw.nyc3.cdn.digitaloceanspaces.com/production/currencies/32/wbtc.webp",
      "webp64": "https://lcw.nyc3.cdn.digitaloceanspaces.com/production/currencies/64/wbtc.webp",
      "exchanges": 83,
      "markets": 147,
      "pairs": 43,
      "categories": [
        "wrapped_tokens"
      ],
      "allTimeHighUSD": 69231.28625326925,
      "circulatingSupply": 118282,
      "totalSupply": 118282,
      "maxSupply": null,
      "website": "https://www.wbtc.network/",
      "links": {
        "whitepaper": "https://wbtc.network/assets/wrapped-tokens-whitepaper.pdf",
        "twitter": "https://twitter.com/WrappedBTC",
        "reddit": null,
        "telegram": null,
        "discord": null,
        "medium": null,
        "instagram": null
      },
      "code": "WBTC",
      "rate": 20374.39077534619,
      "volume": 144549269,
      "cap": 2409923690,
      "delta": {
        "hour": 0.9988,
        "day": 1.0139,
        "week": 1.0415,
        "month": 1.0296,
        "quarter": 0.9259,
        "year": 0.3973
      }
    },
    {
      "name": "Bitcoin Cash",
      "rank": 30,
      "age": 1892,
      "color": "#f1f9f7",
      "png32": "https://lcw.nyc3.cdn.digitaloceanspaces.com/production/currencies/32/bch.png",
      "png64": "https://lcw.nyc3.cdn.digitaloceanspaces.com/production/currencies/64/bch.png",
      "webp32": "https://lcw.nyc3.cdn.digitaloceanspaces.com/production/currencies/32/bch.webp",
      "webp64": "https://lcw.nyc3.cdn.digitaloceanspaces.com/production/currencies/64/bch.webp",
      "exchanges": 95,
      "markets": 214,
      "pairs": 47,
      "categories": [
        "smart_contract_platforms"
      ],
      "allTimeHighUSD": 4355.62,
      "circulatingSupply": 19192924,
      "totalSupply": 19192924,
      "maxSupply": 21000000,
      "website": "https://www.bitcoincash.org/",
      "links": {
        "whitepaper": "https://www.bitcoincash.org/bitcoin.pdf",
        "twitter": null,
        "reddit": "https://reddit.com/r/Bitcoincash",
        "telegram": null,
        "discord": null,
        "medium": null,
        "instagram": null
      },
      "code": "BCH",
      "rate": 122.18423205022953,
      "volume": 120961733,
      "cap": 2345072680,
      "delta": {
        "hour": 0.997,
        "day": 1.0046,
        "week": 1.0667,
        "month": 0.9843,
        "quarter": 1.103,
        "year": 0.208
      }
    },
    {
      "name": "Luna Classic",
      "rank": 31,
      "age": 2087,
      "color": "#fbd35b",
      "png32": "https://lcw.nyc3.cdn.digitaloceanspaces.com/production/currencies/32/lunc.png",
      "png64": "https://lcw.nyc3.cdn.digitaloceanspaces.com/production/currencies/64/lunc.png",
      "webp32": "https://lcw.nyc3.cdn.digitaloceanspaces.com/production/currencies/32/lunc.webp",
      "webp64": "https://lcw.nyc3.cdn.digitaloceanspaces.com/production/currencies/64/lunc.webp",
      "exchanges": 42,
      "markets": 59,
      "pairs": 16,
      "categories": [
        "smart_contract_platforms"
      ],
      "allTimeHighUSD": 118.73761687543433,
      "circulatingSupply": 6536407736539,
      "totalSupply": 6893223341358,
      "maxSupply": null,
      "website": "https://terra.money/",
      "links": {
        "whitepaper": "https://docs.terra.money/",
        "twitter": "https://twitter.com/terra_money",
        "reddit": "https://reddit.com/r/terraluna",
        "telegram": "https://t.me/TerraLunaChat",
        "discord": "https://discord.com/invite/terra-money",
        "medium": "https://medium.com/terra-money",
        "instagram": null
      },
      "code": "LUNC",
      "rate": 0.00030230430243864887,
      "volume": 323541216,
      "cap": 1975984181,
      "delta": {
        "hour": 0.9927,
        "day": 0.9581,
        "week": 1.0788,
        "month": 0.7638,
        "quarter": 2.6367,
        "year": null
      }
    },
    {
      "name": "Flow",
      "rank": 32,
      "age": 614,
      "color": "#f2fcf7",
      "png32": "https://lcw.nyc3.cdn.digitaloceanspaces.com/production/currencies/32/flow.png",
      "png64": "https://lcw.nyc3.cdn.digitaloceanspaces.com/production/currencies/64/flow.png",
      "webp32": "https://lcw.nyc3.cdn.digitaloceanspaces.com/production/currencies/32/flow.webp",
      "webp64": "https://lcw.nyc3.cdn.digitaloceanspaces.com/production/currencies/64/flow.webp",
      "exchanges": 28,
      "markets": 51,
      "pairs": 11,
      "categories": [
        "smart_contract_platforms",
        "wallets",
        "nfts",
        "sports"
      ],
      "allTimeHighUSD": 42.483072856552496,
      "circulatingSupply": 1036200000,
      "totalSupply": 1359340091,
      "maxSupply": null,
      "website": "https://flow.com/",
      "links": {
        "whitepaper": "https://assets.website-files.com/5f6294c0c7a8cdd643b1c820/5f6c23fa8711d751fa6b75f3_FLOW%20token%20economics.pdf",
        "twitter": "https://twitter.com/flow_blockchain",
        "reddit": "https://reddit.com/r/flowtoken",
        "telegram": "https://t.me/flow_blockchain",
        "discord": "https://discord.com/invite/flow",
        "medium": "https://medium.com/@flow_blockchain",
        "instagram": null
      },
      "code": "FLOW",
      "rate": 1.71797401555629,
      "volume": 31948815,
      "cap": 1780164675,
      "delta": {
        "hour": 0.999,
        "day": 1.012,
        "week": 1.0366,
        "month": 0.8944,
        "quarter": 1.0214,
        "year": 0.0873
      }
    },
    {
      "name": "Quant",
      "rank": 33,
      "age": 1517,
      "color": "#ec3b1b",
      "png32": "https://lcw.nyc3.cdn.digitaloceanspaces.com/production/currencies/32/qnt.png",
      "png64": "https://lcw.nyc3.cdn.digitaloceanspaces.com/production/currencies/64/qnt.png",
      "webp32": "https://lcw.nyc3.cdn.digitaloceanspaces.com/production/currencies/32/qnt.webp",
      "webp64": "https://lcw.nyc3.cdn.digitaloceanspaces.com/production/currencies/64/qnt.webp",
      "exchanges": 40,
      "markets": 62,
      "pairs": 15,
      "categories": [
        "smart_contract_platforms"
      ],
      "allTimeHighUSD": 427.17462457402735,
      "circulatingSupply": 12072738,
      "totalSupply": 14612493,
      "maxSupply": 14612491,
      "website": "https://quant.network/",
      "links": {
        "whitepaper": "https://uploads-ssl.webflow.com/6006946fee85fda61f666256/60211c93f1cc59419c779c42_Quant_Overledger_Whitepaper_Sep_2019.pdf",
        "twitter": "https://twitter.com/quant_network",
        "reddit": "https://reddit.com/r/QuantNetwork",
        "telegram": "https://t.me/QuantOverledger",
        "discord": null,
        "medium": "https://quantnetwork.medium.com",
        "instagram": null
      },
      "code": "QNT",
      "rate": 138.48766033889734,
      "volume": 67378925,
      "cap": 1671925240,
      "delta": {
        "hour": 0.9925,
        "day": 0.9894,
        "week": 1.0579,
        "month": 1.4921,
        "quarter": 2.1681,
        "year": 0.4672
      }
    },
    {
      "name": "Filecoin",
      "rank": 34,
      "age": 720,
      "color": "#0492fc",
      "png32": "https://lcw.nyc3.cdn.digitaloceanspaces.com/production/currencies/32/fil.png",
      "png64": "https://lcw.nyc3.cdn.digitaloceanspaces.com/production/currencies/64/fil.png",
      "webp32": "https://lcw.nyc3.cdn.digitaloceanspaces.com/production/currencies/32/fil.webp",
      "webp64": "https://lcw.nyc3.cdn.digitaloceanspaces.com/production/currencies/64/fil.webp",
      "exchanges": 36,
      "markets": 63,
      "pairs": 16,
      "categories": [
        "cloud_hosting",
        "storage"
      ],
      "allTimeHighUSD": 237.64668979882163,
      "circulatingSupply": 293956897,
      "totalSupply": 1972610415,
      "maxSupply": 1972610415,
      "website": "https://filecoin.io/",
      "links": {
        "whitepaper": "https://docs.filecoin.io/",
        "twitter": "https://twitter.com/Filecoin",
        "reddit": "https://reddit.com/r/filecoin",
        "telegram": null,
        "discord": null,
        "medium": null,
        "instagram": null
      },
      "code": "FIL",
      "rate": 5.6319806739442,
      "volume": 41840213,
      "cap": 1655559563,
      "delta": {
        "hour": 0.9975,
        "day": 1.0084,
        "week": 0.9598,
        "month": 0.9152,
        "quarter": 0.9699,
        "year": 0.0806
      }
    },
    {
      "name": "Axie Infinity",
      "rank": 35,
      "age": 700,
      "color": "#0f48b3",
      "png32": "https://lcw.nyc3.cdn.digitaloceanspaces.com/production/currencies/32/axs.png",
      "png64": "https://lcw.nyc3.cdn.digitaloceanspaces.com/production/currencies/64/axs.png",
      "webp32": "https://lcw.nyc3.cdn.digitaloceanspaces.com/production/currencies/32/axs.webp",
      "webp64": "https://lcw.nyc3.cdn.digitaloceanspaces.com/production/currencies/64/axs.webp",
      "exchanges": 60,
      "markets": 93,
      "pairs": 17,
      "categories": [
        "gaming",
        "nfts"
      ],
      "allTimeHighUSD": 164.99042139105435,
      "circulatingSupply": 127444140,
      "totalSupply": 270000000,
      "maxSupply": 270000000,
      "website": "https://axieinfinity.com/",
      "links": {
        "whitepaper": "https://whitepaper.axieinfinity.com/",
        "twitter": "https://twitter.com/axieinfinity",
        "reddit": "https://reddit.com/r/axieinfinity",
        "telegram": "https://t.me/axieinfinity",
        "discord": "https://discord.com/invite/axie",
        "medium": "https://axieinfinity.medium.com/",
        "instagram": "https://www.instagram.com/axieinfinity/"
      },
      "code": "AXS",
      "rate": 12.962750583284897,
      "volume": 59141531,
      "cap": 1652026600,
      "delta": {
        "hour": 0.9993,
        "day": 1.0156,
        "week": 1.0313,
        "month": 0.913,
        "quarter": 0.8472,
        "year": 0.1006
      }
    },
    {
      "name": "Internet Computer",
      "rank": 36,
      "age": 513,
      "color": "#ea594e",
      "png32": "https://lcw.nyc3.cdn.digitaloceanspaces.com/production/currencies/32/icp.png",
      "png64": "https://lcw.nyc3.cdn.digitaloceanspaces.com/production/currencies/64/icp.png",
      "webp32": "https://lcw.nyc3.cdn.digitaloceanspaces.com/production/currencies/32/icp.webp",
      "webp64": "https://lcw.nyc3.cdn.digitaloceanspaces.com/production/currencies/64/icp.webp",
      "exchanges": 38,
      "markets": 72,
      "pairs": 14,
      "categories": [
        "cloud_hosting",
        "storage"
      ],
      "allTimeHighUSD": 494.5636424153892,
      "circulatingSupply": 262468469,
      "totalSupply": 471245633,
      "maxSupply": 471266671,
      "website": "https://dfinity.org/",
      "links": {
        "whitepaper": "https://sdk.dfinity.org/docs/interface-spec/index.html",
        "twitter": "https://twitter.com/dfinity",
        "reddit": "https://reddit.com/r/dfinity",
        "telegram": "https://t.me/dfinity/",
        "discord": null,
        "medium": "https://medium.com/dfinity-network-blog",
        "instagram": null
      },
      "code": "ICP",
      "rate": 6.12365480329225,
      "volume": 38254993,
      "cap": 1607266301,
      "delta": {
        "hour": 0.9985,
        "day": 1.0015,
        "week": 1.0056,
        "month": 0.9161,
        "quarter": 0.9776,
        "year": 0.1141
      }
    },
    {
      "name": "VeChain",
      "rank": 37,
      "age": 1871,
      "color": "#6488e1",
      "png32": "https://lcw.nyc3.cdn.digitaloceanspaces.com/production/currencies/32/vet.png",
      "png64": "https://lcw.nyc3.cdn.digitaloceanspaces.com/production/currencies/64/vet.png",
      "webp32": "https://lcw.nyc3.cdn.digitaloceanspaces.com/production/currencies/32/vet.webp",
      "webp64": "https://lcw.nyc3.cdn.digitaloceanspaces.com/production/currencies/64/vet.webp",
      "exchanges": 39,
      "markets": 106,
      "pairs": 39,
      "categories": [
        "logistics",
        "ai",
        "iot",
        "smart_contract_platforms"
      ],
      "allTimeHighUSD": 0.26773718608293,
      "circulatingSupply": 66760741299,
      "totalSupply": 85985041177,
      "maxSupply": 86712634466,
      "website": "https://www.vechain.org/",
      "links": {
        "whitepaper": "https://cdn.vechain.com/vechain_ico_ideas_of_development_en.pdf",
        "twitter": "https://twitter.com/vechainofficial",
        "reddit": "https://reddit.com/r/vechain",
        "telegram": "https://t.me/vechain_official_english",
        "discord": null,
        "medium": null,
        "instagram": null
      },
      "code": "VET",
      "rate": 0.024035067138768764,
      "volume": 63550672,
      "cap": 1604598899,
      "delta": {
        "hour": 0.9995,
        "day": 1.018,
        "week": 1.043,
        "month": 0.9687,
        "quarter": 0.9779,
        "year": 0.2176
      }
    },
    {
      "name": "Decentraland",
      "rank": 38,
      "age": 1845,
      "color": "#f64e5c",
      "png32": "https://lcw.nyc3.cdn.digitaloceanspaces.com/production/currencies/32/mana.png",
      "png64": "https://lcw.nyc3.cdn.digitaloceanspaces.com/production/currencies/64/mana.png",
      "webp32": "https://lcw.nyc3.cdn.digitaloceanspaces.com/production/currencies/32/mana.webp",
      "webp64": "https://lcw.nyc3.cdn.digitaloceanspaces.com/production/currencies/64/mana.webp",
      "exchanges": 81,
      "markets": 145,
      "pairs": 24,
      "categories": [
        "metaverse",
        "vr",
        "gaming",
        "nfts"
      ],
      "allTimeHighUSD": 5.871183877218146,
      "circulatingSupply": 2193500227,
      "totalSupply": 2193500227,
      "maxSupply": 2805886393,
      "website": "https://decentraland.org/",
      "links": {
        "whitepaper": "https://decentraland.org/whitepaper.pdf",
        "twitter": "https://twitter.com/decentraland",
        "reddit": "https://reddit.com/r/decentraland",
        "telegram": "https://t.me/dcl_market",
        "discord": "https://decentraland.org/discord/",
        "medium": "https://medium.com/@decentraland",
        "instagram": "https://www.instagram.com/decentralandoficial/"
      },
      "code": "MANA",
      "rate": 0.7137921950266767,
      "volume": 104862954,
      "cap": 1565703342,
      "delta": {
        "hour": 0.9982,
        "day": 1.0082,
        "week": 1.0076,
        "month": 0.8934,
        "quarter": 0.7654,
        "year": 0.9375
      }
    },
    {
      "name": "Chain",
      "rank": 39,
      "age": 198,
      "color": "#07080e",
      "png32": "https://lcw.nyc3.cdn.digitaloceanspaces.com/production/currencies/32/xcn.png",
      "png64": "https://lcw.nyc3.cdn.digitaloceanspaces.com/production/currencies/64/xcn.png",
      "webp32": "https://lcw.nyc3.cdn.digitaloceanspaces.com/production/currencies/32/xcn.webp",
      "webp64": "https://lcw.nyc3.cdn.digitaloceanspaces.com/production/currencies/64/xcn.webp",
      "exchanges": 10,
      "markets": 17,
      "pairs": 6,
      "categories": [
        "cloud_hosting"
      ],
      "allTimeHighUSD": 0.20682316364750936,
      "circulatingSupply": 21479256391,
      "totalSupply": 53467135350,
      "maxSupply": 68892017046,
      "website": "https://chain.com/",
      "links": {
        "whitepaper": "https://chain.com/WhitePaper.pdf",
        "twitter": "https://twitter.com/Chain",
        "reddit": null,
        "telegram": "https://t.me/Chain",
        "discord": "https://discord.com/invite/ChainOfficial",
        "medium": "https://blog.chain.com/",
        "instagram": "https://www.instagram.com/Chain/"
      },
      "code": "XCN",
      "rate": 0.06936297079937384,
      "volume": 11921720,
      "cap": 1489865034,
      "delta": {
        "hour": 0.9892,
        "day": 0.9281,
        "week": 0.935,
        "month": 0.9194,
        "quarter": 0.7689,
        "year": null
      }
    },
    {
      "name": "ApeCoin",
      "rank": 40,
      "age": 202,
      "color": "#ecf0f6",
      "png32": "https://lcw.nyc3.cdn.digitaloceanspaces.com/production/currencies/32/ape.png",
      "png64": "https://lcw.nyc3.cdn.digitaloceanspaces.com/production/currencies/64/ape.png",
      "webp32": "https://lcw.nyc3.cdn.digitaloceanspaces.com/production/currencies/32/ape.webp",
      "webp64": "https://lcw.nyc3.cdn.digitaloceanspaces.com/production/currencies/64/ape.webp",
      "exchanges": 68,
      "markets": 111,
      "pairs": 20,
      "categories": [
        "governance",
        "nfts",
        "gaming"
      ],
      "allTimeHighUSD": 26.904219658917285,
      "circulatingSupply": 277500000,
      "totalSupply": 1000000000,
      "maxSupply": 1000000000,
      "website": "https://apecoin.com/",
      "links": {
        "whitepaper": null,
        "twitter": "https://twitter.com/apecoin",
        "reddit": "https://reddit.com/r/BoredApeYachtClub",
        "telegram": null,
        "discord": "https://discord.com/invite/wjH7hGz2yS",
        "medium": "https://boredapeyachtclub.medium.com/",
        "instagram": "https://www.instagram.com/boredapeyachtclub/"
      },
      "code": "APE",
      "rate": 5.3677859407826,
      "volume": 170763265,
      "cap": 1489560599,
      "delta": {
        "hour": 0.9944,
        "day": 1.0294,
        "week": 0.987,
        "month": 1.1333,
        "quarter": 1.0377,
        "year": null
      }
    },
    {
      "name": "Hedera Hashgraph",
      "rank": 41,
      "age": 1101,
      "color": "#f8f8f8",
      "png32": "https://lcw.nyc3.cdn.digitaloceanspaces.com/production/currencies/32/hbar.png",
      "png64": "https://lcw.nyc3.cdn.digitaloceanspaces.com/production/currencies/64/hbar.png",
      "webp32": "https://lcw.nyc3.cdn.digitaloceanspaces.com/production/currencies/32/hbar.webp",
      "webp64": "https://lcw.nyc3.cdn.digitaloceanspaces.com/production/currencies/64/hbar.webp",
      "exchanges": 33,
      "markets": 60,
      "pairs": 14,
      "categories": [
        "smart_contract_platforms"
      ],
      "allTimeHighUSD": 0.569398985191319,
      "circulatingSupply": 24345950930,
      "totalSupply": 50000000000,
      "maxSupply": 50000000000,
      "website": "https://hedera.com/",
      "links": {
        "whitepaper": "https://hedera.com/papers",
        "twitter": "https://twitter.com/hedera",
        "reddit": "https://reddit.com/r/hashgraph",
        "telegram": "https://t.me/hederahashgraph",
        "discord": "https://discord.com/invite/EC2GY8ueRk",
        "medium": "https://medium.com/hedera",
        "instagram": "https://www.instagram.com/hashgraph/"
      },
      "code": "HBAR",
      "rate": 0.0587689189310004,
      "volume": 34005705,
      "cap": 1430785217,
      "delta": {
        "hour": 0.9968,
        "day": 1.0133,
        "week": 1.0039,
        "month": 0.9337,
        "quarter": 0.8978,
        "year": 0.1526
      }
    },
    {
      "name": "Frax",
      "rank": 42,
      "age": 653,
      "color": "#040404",
      "png32": "https://lcw.nyc3.cdn.digitaloceanspaces.com/production/currencies/32/frax.png",
      "png64": "https://lcw.nyc3.cdn.digitaloceanspaces.com/production/currencies/64/frax.png",
      "webp32": "https://lcw.nyc3.cdn.digitaloceanspaces.com/production/currencies/32/frax.webp",
      "webp64": "https://lcw.nyc3.cdn.digitaloceanspaces.com/production/currencies/64/frax.webp",
      "exchanges": 18,
      "markets": 36,
      "pairs": 17,
      "categories": [
        "stablecoins"
      ],
      "allTimeHighUSD": 2.3623089418913477,
      "circulatingSupply": 1355617599,
      "totalSupply": 1358975653,
      "maxSupply": null,
      "website": "https://frax.finance",
      "links": {
        "whitepaper": "https://docs.frax.finance/overview",
        "twitter": "https://twitter.com/fraxfinance",
        "reddit": "https://reddit.com/r/fraxfinance",
        "telegram": "https://t.me/fraxfinance",
        "discord": "https://discord.com/invite/srafCj96",
        "medium": "https://fraxfinancecommunity.medium.com/",
        "instagram": null
      },
      "code": "FRAX",
      "rate": 1.0022151984471985,
      "volume": 5921479,
      "cap": 1358620561,
      "delta": {
        "hour": 0.9999,
        "day": 1.0083,
        "week": 1.0014,
        "month": 1.0048,
        "quarter": 1.0026,
        "year": 1.0023
      }
    },
    {
      "name": "Tezos",
      "rank": 43,
      "age": 1650,
      "color": "#2c84fc",
      "png32": "https://lcw.nyc3.cdn.digitaloceanspaces.com/production/currencies/32/xtz.png",
      "png64": "https://lcw.nyc3.cdn.digitaloceanspaces.com/production/currencies/64/xtz.png",
      "webp32": "https://lcw.nyc3.cdn.digitaloceanspaces.com/production/currencies/32/xtz.webp",
      "webp64": "https://lcw.nyc3.cdn.digitaloceanspaces.com/production/currencies/64/xtz.webp",
      "exchanges": 47,
      "markets": 92,
      "pairs": 27,
      "categories": [
        "smart_contract_platforms"
      ],
      "allTimeHighUSD": 9.085601324153052,
      "circulatingSupply": 911476491,
      "totalSupply": 932968355,
      "maxSupply": null,
      "website": "https://www.tezos.com/",
      "links": {
        "whitepaper": "https://tezos.gitlab.io/",
        "twitter": "https://twitter.com/tezos",
        "reddit": "https://reddit.com/r/tezos",
        "telegram": "https://t.me/tezosplatform",
        "discord": "https://discord.gg/e6dCF7B",
        "medium": "https://medium.com/tezos",
        "instagram": null
      },
      "code": "XTZ",
      "rate": 1.446765148757565,
      "volume": 12836976,
      "cap": 1318692421,
      "delta": {
        "hour": 1.0008,
        "day": 0.9999,
        "week": 1.0044,
        "month": 0.9235,
        "quarter": 0.9226,
        "year": 0.1899
      }
    },
    {
      "name": "The Sandbox",
      "rank": 44,
      "age": 781,
      "color": "#0598f5",
      "png32": "https://lcw.nyc3.cdn.digitaloceanspaces.com/production/currencies/32/sand.png",
      "png64": "https://lcw.nyc3.cdn.digitaloceanspaces.com/production/currencies/64/sand.png",
      "webp32": "https://lcw.nyc3.cdn.digitaloceanspaces.com/production/currencies/32/sand.webp",
      "webp64": "https://lcw.nyc3.cdn.digitaloceanspaces.com/production/currencies/64/sand.webp",
      "exchanges": 74,
      "markets": 124,
      "pairs": 26,
      "categories": [
        "metaverse",
        "gaming",
        "nfts",
        "governance"
      ],
      "allTimeHighUSD": 8.35315043328023,
      "circulatingSupply": 1499470209,
      "totalSupply": 3000000000,
      "maxSupply": null,
      "website": "https://www.sandbox.game/en/about/sand/",
      "links": {
        "whitepaper": "https://installers.sandbox.game/The_Sandbox_Whitepaper_2020.pdf?_ga=2.143273333.1365935332.1650076062-204075722.1650076062",
        "twitter": "https://twitter.com/TheSandboxGame",
        "reddit": "https://reddit.com/r/TheSandboxGaming",
        "telegram": "https://t.me/sandboxgame",
        "discord": "https://discord.com/invite/vAe4zvY",
        "medium": "https://medium.com/sandbox-game",
        "instagram": "https://instagram.com/thesandboxgame"
      },
      "code": "SAND",
      "rate": 0.8705640219344063,
      "volume": 186200839,
      "cap": 1305384816,
      "delta": {
        "hour": 0.9988,
        "day": 1.0174,
        "week": 1.0187,
        "month": 0.9081,
        "quarter": 0.6821,
        "year": 1.0847
      }
    },
    {
      "name": "Elrond",
      "rank": 45,
      "age": 762,
      "color": "#060606",
      "png32": "https://lcw.nyc3.cdn.digitaloceanspaces.com/production/currencies/32/egld.png",
      "png64": "https://lcw.nyc3.cdn.digitaloceanspaces.com/production/currencies/64/egld.png",
      "webp32": "https://lcw.nyc3.cdn.digitaloceanspaces.com/production/currencies/32/egld.webp",
      "webp64": "https://lcw.nyc3.cdn.digitaloceanspaces.com/production/currencies/64/egld.webp",
      "exchanges": 19,
      "markets": 40,
      "pairs": 19,
      "categories": [
        "smart_contract_platforms"
      ],
      "allTimeHighUSD": 548.0865877630855,
      "circulatingSupply": 23627030,
      "totalSupply": 24390902,
      "maxSupply": null,
      "website": "https://elrond.com/",
      "links": {
        "whitepaper": "https://elrond.com/assets/files/elrond-whitepaper.pdf",
        "twitter": "https://twitter.com/elrondnetwork",
        "reddit": "https://reddit.com/r/elrondnetwork",
        "telegram": "https://t.me/ElrondNetwork",
        "discord": null,
        "medium": null,
        "instagram": null
      },
      "code": "EGLD",
      "rate": 55.166469444397315,
      "volume": 39846703,
      "cap": 1303419829,
      "delta": {
        "hour": 0.9927,
        "day": 1.0083,
        "week": 1.1626,
        "month": 1.0714,
        "quarter": 0.9809,
        "year": 0.2328
      }
    },
    {
      "name": "EOS",
      "rank": 46,
      "age": 1922,
      "color": "#ebebeb",
      "png32": "https://lcw.nyc3.cdn.digitaloceanspaces.com/production/currencies/32/eos.png",
      "png64": "https://lcw.nyc3.cdn.digitaloceanspaces.com/production/currencies/64/eos.png",
      "webp32": "https://lcw.nyc3.cdn.digitaloceanspaces.com/production/currencies/32/eos.webp",
      "webp64": "https://lcw.nyc3.cdn.digitaloceanspaces.com/production/currencies/64/eos.webp",
      "exchanges": 78,
      "markets": 202,
      "pairs": 37,
      "categories": [
        "smart_contract_platforms"
      ],
      "allTimeHighUSD": 23.95565521183252,
      "circulatingSupply": 1010749488,
      "totalSupply": 1010749488,
      "maxSupply": null,
      "website": "https://eos.io/",
      "links": {
        "whitepaper": "https://github.com/EOSIO/Documentation/blob/master/TechnicalWhitePaper.md",
        "twitter": "https://twitter.com/block_one_",
        "reddit": "https://reddit.com/r/EOS",
        "telegram": "https://t.me/EOSProject",
        "discord": null,
        "medium": "https://medium.com/eosio",
        "instagram": null
      },
      "code": "EOS",
      "rate": 1.1917654966719653,
      "volume": 150929873,
      "cap": 1204576366,
      "delta": {
        "hour": 0.9994,
        "day": 1.0002,
        "week": 1.0016,
        "month": 0.7735,
        "quarter": 1.1324,
        "year": 0.2568
      }
    },
    {
      "name": "Chiliz",
      "rank": 47,
      "age": 1183,
      "color": "#cc0524",
      "png32": "https://lcw.nyc3.cdn.digitaloceanspaces.com/production/currencies/32/chz.png",
      "png64": "https://lcw.nyc3.cdn.digitaloceanspaces.com/production/currencies/64/chz.png",
      "webp32": "https://lcw.nyc3.cdn.digitaloceanspaces.com/production/currencies/32/chz.webp",
      "webp64": "https://lcw.nyc3.cdn.digitaloceanspaces.com/production/currencies/64/chz.webp",
      "exchanges": 71,
      "markets": 158,
      "pairs": 57,
      "categories": [
        "nfts",
        "sports"
      ],
      "allTimeHighUSD": 0.8945843938439773,
      "circulatingSupply": 5344064580,
      "totalSupply": 8888888888,
      "maxSupply": 8888888888,
      "website": "https://www.chiliz.com/",
      "links": {
        "whitepaper": "https://www.chiliz.com/docs/CHZ_whitepaper.pdf",
        "twitter": "https://twitter.com/chiliz",
        "reddit": null,
        "telegram": "https://t.me/ChilizNews",
        "discord": "https://discord.gg/QsJ8dAnsDy",
        "medium": "https://medium.com/chiliz",
        "instagram": "http://www.instagram.com/chilizdotcom"
      },
      "code": "CHZ",
      "rate": 0.21893542145815909,
      "volume": 275140432,
      "cap": 1170005031,
      "delta": {
        "hour": 0.9957,
        "day": 1.0169,
        "week": 0.9178,
        "month": 1.0547,
        "quarter": 2.1137,
        "year": 0.7196
      }
    },
    {
      "name": "Aave",
      "rank": 48,
      "age": 722,
      "color": "#688cb5",
      "png32": "https://lcw.nyc3.cdn.digitaloceanspaces.com/production/currencies/32/aave.png",
      "png64": "https://lcw.nyc3.cdn.digitaloceanspaces.com/production/currencies/64/aave.png",
      "webp32": "https://lcw.nyc3.cdn.digitaloceanspaces.com/production/currencies/32/aave.webp",
      "webp64": "https://lcw.nyc3.cdn.digitaloceanspaces.com/production/currencies/64/aave.webp",
      "exchanges": 95,
      "markets": 177,
      "pairs": 27,
      "categories": [
        "lending",
        "governance",
        "yield_aggregators"
      ],
      "allTimeHighUSD": 663.2190116456594,
      "circulatingSupply": 14116624,
      "totalSupply": 16000000,
      "maxSupply": 16000000,
      "website": "https://aave.com/",
      "links": {
        "whitepaper": "https://github.com/aave/protocol-v2/blob/master/aave-v2-whitepaper.pdf",
        "twitter": "https://twitter.com/AaveAave",
        "reddit": "https://reddit.com/r/Aave_Official",
        "telegram": "https://t.me/Aavesome",
        "discord": "https://discord.com/invite/adPfquZDZc",
        "medium": "https://medium.com/aave",
        "instagram": "https://instagram.com/aave.aave"
      },
      "code": "AAVE",
      "rate": 79.61328779009891,
      "volume": 96260304,
      "cap": 1123870849,
      "delta": {
        "hour": 0.9992,
        "day": 1.0237,
        "week": 1.029,
        "month": 0.8679,
        "quarter": 1.103,
        "year": 0.2661
      }
    },
    {
      "name": "Theta Network",
      "rank": 49,
      "age": 1722,
      "color": "#25ced3",
      "png32": "https://lcw.nyc3.cdn.digitaloceanspaces.com/production/currencies/32/theta.png",
      "png64": "https://lcw.nyc3.cdn.digitaloceanspaces.com/production/currencies/64/theta.png",
      "webp32": "https://lcw.nyc3.cdn.digitaloceanspaces.com/production/currencies/32/theta.webp",
      "webp64": "https://lcw.nyc3.cdn.digitaloceanspaces.com/production/currencies/64/theta.webp",
      "exchanges": 30,
      "markets": 63,
      "pairs": 16,
      "categories": [
        "social_media",
        "nfts",
        "streaming"
      ],
      "allTimeHighUSD": 15.710482367125962,
      "circulatingSupply": 1000000000,
      "totalSupply": 1000000000,
      "maxSupply": 1000000000,
      "website": "https://www.thetatoken.org/",
      "links": {
        "whitepaper": "https://s3.us-east-2.amazonaws.com/assets.thetatoken.org/Theta-white-paper-latest.pdf",
        "twitter": "https://twitter.com/theta_network",
        "reddit": "https://reddit.com/r/thetatoken",
        "telegram": "https://t.me/joinchat/Gt6mbxJb-2XukwGA_atLjg",
        "discord": "https://discord.com/invite/nC8mCkgEmV",
        "medium": "https://medium.com/theta-network",
        "instagram": "https://www.instagram.com/thetanetworktoken/"
      },
      "code": "THETA",
      "rate": 1.1073319536009936,
      "volume": 27357140,
      "cap": 1107331954,
      "delta": {
        "hour": 0.9992,
        "day": 1.0333,
        "week": 1.0131,
        "month": 0.9379,
        "quarter": 0.8594,
        "year": 0.1647
      }
    },
    {
      "name": "Bitcoin SV",
      "rank": 50,
      "age": 1421,
      "color": "#ebb304",
      "png32": "https://lcw.nyc3.cdn.digitaloceanspaces.com/production/currencies/32/bsv.png",
      "png64": "https://lcw.nyc3.cdn.digitaloceanspaces.com/production/currencies/64/bsv.png",
      "webp32": "https://lcw.nyc3.cdn.digitaloceanspaces.com/production/currencies/32/bsv.webp",
      "webp64": "https://lcw.nyc3.cdn.digitaloceanspaces.com/production/currencies/64/bsv.webp",
      "exchanges": 29,
      "markets": 49,
      "pairs": 10,
      "categories": [
        "smart_contract_platforms"
      ],
      "allTimeHighUSD": 491.46694659606356,
      "circulatingSupply": 19188957,
      "totalSupply": 19188957,
      "maxSupply": 21000000,
      "website": "https://bitcoinsv.io/",
      "links": {
        "whitepaper": null,
        "twitter": "https://twitter.com/BitcoinSVNode",
        "reddit": null,
        "telegram": null,
        "discord": null,
        "medium": null,
        "instagram": null
      },
      "code": "BSV",
      "rate": 50.06449899321164,
      "volume": 15687738,
      "cap": 960685518,
      "delta": {
        "hour": 0.9983,
        "day": 1.0158,
        "week": 0.9998,
        "month": 0.9354,
        "quarter": 0.8652,
        "year": 0.3371
      }
    }
  ]